[{"id":"r-cfluxplanqbnkv","companyId":"c-fluxplatuiab5k","stage":"Seed","amt":3278742,"leadId":"f-mooretho7y9aeg","leadName":"Moore & Thomas Ventures","status":"closed","closeDate":"2024-02-20","asOf":"2026-01-21T00:38:52.666Z"},{"id":"r-cfluxplaffmqc9","companyId":"c-fluxplatuiab5k","stage":"Seed","amt":4497394,"leadId":"f-johnsonkcpopjz","leadName":"Johnson & King Partners","status":"active","closeDate":"2024-10-30","asOf":"2026-01-11T00:38:52.666Z"},{"id":"r-cedgeaig48p5hq","companyId":"c-edgeaigogqy9","stage":"Pre-seed","amt":1583158,"leadId":"f-nextpartddv71w","leadName":"Next Partners","status":"closed","closeDate":"2025-07-16","asOf":"2026-01-22T00:38:52.666Z"},{"id":"r-cedgeaigh1cue4","companyId":"c-edgeaigogqy9","stage":"Pre-seed","amt":4024715,"leadId":"f-smithkindgpma9","leadName":"Smith & King Fund","status":"closed","closeDate":"2025-09-30","asOf":"2026-01-03T00:38:52.666Z"},{"id":"r-cedgeaigkj8ujr","companyId":"c-edgeaigogqy9","stage":"Pre-seed","amt":2183177,"leadId":"f-nexuspar5l3wzg","leadName":"Nexus Partners","status":"active","closeDate":"2025-02-04","asOf":"2026-01-28T00:38:52.666Z"},{"id":"r-ccloudopczc6q1","companyId":"c-cloudopsej2b4m","stage":"Pre-seed","amt":1079094,"leadId":"f-orbitcap7bn0g4","leadName":"Orbit Capital","status":"closed","closeDate":"2025-10-30","asOf":"2026-01-08T00:38:52.666Z"},{"id":"r-ccloudopkb8zfp","companyId":"c-cloudopsej2b4m","stage":"Pre-seed","amt":2996668,"leadId":"f-alphavclptg93","leadName":"Alpha VC","status":"closed","closeDate":"2024-12-22","asOf":"2026-01-06T00:38:52.666Z"},{"id":"r-ccloudopqftypc","companyId":"c-cloudopsej2b4m","stage":"Pre-seed","amt":2084701,"leadId":"f-taylorpaeyq6wa","leadName":"Taylor Partners","status":"active","closeDate":"2025-01-14","asOf":"2026-01-28T00:38:52.666Z"},{"id":"r-catlaspljk1wtn","companyId":"c-atlasplaeqm1np","stage":"Series A","amt":7264782,"leadId":"f-primefuni6gmnx","leadName":"Prime Fund","status":"closed","closeDate":"2024-11-09","asOf":"2026-01-28T00:38:52.666Z"},{"id":"r-catlasplt1ofli","companyId":"c-atlasplaeqm1np","stage":"Series A","amt":5362362,"leadId":"f-alphavc7rdwvv","leadName":"Alpha VC","status":"active","closeDate":"2025-06-11","asOf":"2026-01-24T00:38:52.666Z"},{"id":"r-cfluxopsu1hnne","companyId":"c-fluxopsf2lpjc","stage":"Series B","amt":45887447,"leadId":"f-patelvcc6nfay","leadName":"Patel VC","status":"closed","closeDate":"2025-09-26","asOf":"2026-01-17T00:38:52.666Z"},{"id":"r-cfluxops6m61pl","companyId":"c-fluxopsf2lpjc","stage":"Series B","amt":15518120,"leadId":"f-betacapiuy4l2w","leadName":"Beta Capital","status":"active","closeDate":"2025-06-15","asOf":"2026-01-11T00:38:52.666Z"},{"id":"r-cprismclx993hs","companyId":"c-prismcloihfl4p","stage":"Pre-seed","amt":1339865,"leadId":"f-kingjohna4ot7g","leadName":"King & Johnson Capital","status":"closed","closeDate":"2025-04-28","asOf":"2026-01-18T00:38:52.666Z"},{"id":"r-cflowpladoonvg","companyId":"c-flowplatw44z89","stage":"Series A","amt":24937236,"leadId":"f-helixvcz4qa8g","leadName":"Helix VC","status":"closed","closeDate":"2024-12-11","asOf":"2026-01-05T00:38:52.666Z"},{"id":"r-cflowpla3288lu","companyId":"c-flowplatw44z89","stage":"Series A","amt":14877977,"leadId":"f-linkpartth8gco","leadName":"Link Partners","status":"closed","closeDate":"2025-06-09","asOf":"2026-01-07T00:38:52.666Z"},{"id":"r-cflowpla0f3r5o","companyId":"c-flowplatw44z89","stage":"Series A","amt":18857503,"leadId":"f-newventufwy7g4","leadName":"New Ventures","status":"closed","closeDate":"2025-08-08","asOf":"2026-01-26T00:38:52.666Z"},{"id":"r-cvectorsplcsw9","companyId":"c-vectorsyroedc5","stage":"Seed","amt":9764142,"leadId":"f-cipherca48o3ij","leadName":"Cipher Capital","status":"closed","closeDate":"2025-11-10","asOf":"2026-01-22T00:38:52.666Z"},{"id":"r-cvectors209yj9","companyId":"c-vectorsyroedc5","stage":"Seed","amt":3460149,"leadId":"f-chenjackmizg7x","leadName":"Chen & Jackson Investments","status":"closed","closeDate":"2025-07-15","asOf":"2026-01-12T00:38:52.666Z"},{"id":"r-cstackapgyy7w2","companyId":"c-stackappy39dhe","stage":"Pre-seed","amt":3795921,"leadId":"f-thompsonmv39hv","leadName":"Thompson Investments","status":"active","closeDate":"2025-09-05","asOf":"2026-01-22T00:38:52.666Z"},{"id":"r-cstackapgalmer","companyId":"c-stackappy39dhe","stage":"Pre-seed","amt":3474810,"leadId":"f-scottvenjptxew","leadName":"Scott Ventures","status":"active","closeDate":"2025-07-19","asOf":"2026-02-01T00:38:52.666Z"},{"id":"r-cstackapyld6o7","companyId":"c-stackappy39dhe","stage":"Pre-seed","amt":1180835,"leadId":"f-purecapi85d18s","leadName":"Pure Capital","status":"closed","closeDate":"2024-07-13","asOf":"2026-01-22T00:38:52.666Z"},{"id":"r-cnexusif21b5ty","companyId":"c-nexusifyxlujdw","stage":"Series A","amt":12947300,"leadId":"f-martinan3dbmmp","leadName":"Martin & Anderson Ventures","status":"active","closeDate":"2024-11-02","asOf":"2026-01-29T00:38:52.666Z"},{"id":"r-cnexusif8vr3ws","companyId":"c-nexusifyxlujdw","stage":"Series A","amt":12914308,"leadId":"f-scottvenjptxew","leadName":"Scott Ventures","status":"closed","closeDate":"2025-10-05","asOf":"2026-01-26T00:38:52.666Z"},{"id":"r-cnexusif20r0kr","companyId":"c-nexusifyxlujdw","stage":"Series A","amt":18802085,"leadId":"f-syncinvef9urd0","leadName":"Sync Investments","status":"closed","closeDate":"2024-11-26","asOf":"2026-01-19T00:38:52.666Z"},{"id":"r-cclearflg52qw8","companyId":"c-clearflov6sylh","stage":"Pre-seed","amt":2633038,"leadId":"f-nextpart0t887j","leadName":"Next Partners","status":"closed","closeDate":"2025-07-14","asOf":"2026-01-15T00:38:52.666Z"},{"id":"r-cclearflqr69bi","companyId":"c-clearflov6sylh","stage":"Pre-seed","amt":2080577,"leadId":"f-thompsonce4bwi","leadName":"Thompson Investments","status":"closed","closeDate":"2024-12-29","asOf":"2026-01-04T00:38:52.666Z"},{"id":"r-czephyri7ruyr2","companyId":"c-zephyrioghr3gi","stage":"Seed","amt":7602575,"leadId":"f-adamslewyds6km","leadName":"Adams & Lewis Partners","status":"active","closeDate":"2024-08-13","asOf":"2026-01-12T00:38:52.666Z"},{"id":"r-czephyriuq4nbg","companyId":"c-zephyrioghr3gi","stage":"Seed","amt":8430740,"leadId":"f-pulsefunbobr79","leadName":"Pulse Fund","status":"closed","closeDate":"2024-08-11","asOf":"2026-01-30T00:38:52.666Z"},{"id":"r-csyncai0q71620","companyId":"c-syncai09gsta","stage":"Series A","amt":20479872,"leadId":"f-kinginveq4umu5","leadName":"King Investments","status":"closed","closeDate":"2025-05-25","asOf":"2026-01-26T00:38:52.666Z"},{"id":"r-csyncai0q3riyr","companyId":"c-syncai09gsta","stage":"Series A","amt":23711966,"leadId":"f-cipherin7dqn5z","leadName":"Cipher Investments","status":"closed","closeDate":"2024-06-04","asOf":"2026-01-11T00:38:52.666Z"},{"id":"r-csyncai0cv4muz","companyId":"c-syncai09gsta","stage":"Series A","amt":11963170,"leadId":"f-clearcap6ynhi8","leadName":"Clear Capital","status":"closed","closeDate":"2025-01-04","asOf":"2026-01-15T00:38:52.666Z"},{"id":"r-cedgeaienkpgsc","companyId":"c-edgeaieyc63a","stage":"Series A","amt":11342020,"leadId":"f-kimandernx3hvh","leadName":"Kim & Anderson Ventures","status":"active","closeDate":"2024-06-17","asOf":"2026-01-06T00:38:52.666Z"},{"id":"r-cedgeaie05md8r","companyId":"c-edgeaieyc63a","stage":"Series A","amt":21608704,"leadId":"f-thomascahf8600","leadName":"Thomas Capital","status":"active","closeDate":"2024-03-22","asOf":"2026-01-14T00:38:52.666Z"},{"id":"r-csparkclzlqx25","companyId":"c-sparkclokuvu2d","stage":"Pre-seed","amt":989996,"leadId":"f-nextinveowy9nh","leadName":"Next Investments","status":"closed","closeDate":"2025-07-18","asOf":"2026-02-01T00:38:52.666Z"},{"id":"r-cpulsedaajx7ws","companyId":"c-pulsedatp08q5s","stage":"Series A","amt":23946630,"leadId":"f-netfundq3eu2u","leadName":"Net Fund","status":"closed","closeDate":"2024-03-06","asOf":"2026-01-11T00:38:52.666Z"},{"id":"r-csmartlaktgowu","companyId":"c-smartlab51eqrg","stage":"Pre-seed","amt":4723718,"leadId":"f-taylorch3s2lrh","leadName":"Taylor & Chen Partners","status":"active","closeDate":"2024-10-14","asOf":"2026-01-23T00:38:52.666Z"},{"id":"r-csmartlar3gmv6","companyId":"c-smartlab51eqrg","stage":"Pre-seed","amt":4028841,"leadId":"f-nextpartukscty","leadName":"Next Partners","status":"active","closeDate":"2025-05-03","asOf":"2026-01-05T00:38:52.666Z"},{"id":"r-csmartlaldext8","companyId":"c-smartlab51eqrg","stage":"Pre-seed","amt":3734409,"leadId":"f-netcapitmncj7n","leadName":"Net Capital","status":"closed","closeDate":"2024-04-21","asOf":"2026-01-06T00:38:52.666Z"},{"id":"r-clinkappoue72c","companyId":"c-linkapp2lse38","stage":"Series A","amt":10615428,"leadId":"f-linkinve6am1ts","leadName":"Link Investments","status":"closed","closeDate":"2025-08-20","asOf":"2026-01-17T00:38:52.666Z"},{"id":"r-cvertexbjvcecb","companyId":"c-vertexbalkhyzm","stage":"Pre-seed","amt":1301607,"leadId":"f-clearfunbumkut","leadName":"Clear Fund","status":"closed","closeDate":"2024-05-14","asOf":"2026-01-14T00:38:52.666Z"},{"id":"r-cvertexbx8az9a","companyId":"c-vertexbalkhyzm","stage":"Pre-seed","amt":4213654,"leadId":"f-nextvcji2x8i","leadName":"Next VC","status":"closed","closeDate":"2024-07-22","asOf":"2026-01-18T00:38:52.666Z"},{"id":"r-ccoreclovzwpf1","companyId":"c-corecloukd7zqx","stage":"Pre-seed","amt":2689841,"leadId":"f-alphavclptg93","leadName":"Alpha VC","status":"active","closeDate":"2025-03-04","asOf":"2026-01-03T00:38:52.666Z"},{"id":"r-ccorecloc518vc","companyId":"c-corecloukd7zqx","stage":"Pre-seed","amt":3742856,"leadId":"f-betafundtt87v1","leadName":"Beta Fund","status":"closed","closeDate":"2024-06-29","asOf":"2026-01-26T00:38:52.666Z"},{"id":"r-ccoreclodv1izw","companyId":"c-corecloukd7zqx","stage":"Pre-seed","amt":3437741,"leadId":"f-bakerlee1k7az7","leadName":"Baker & Lee Partners","status":"closed","closeDate":"2025-09-24","asOf":"2026-01-05T00:38:52.666Z"},{"id":"r-csyncclozscy2g","companyId":"c-syncclouex04dp","stage":"Seed","amt":9956677,"leadId":"f-betainve2vorik","leadName":"Beta Investments","status":"closed","closeDate":"2025-12-22","asOf":"2026-01-25T00:38:52.666Z"},{"id":"r-cclearflvw8aaq","companyId":"c-clearflofn0e0v","stage":"Seed","amt":9462339,"leadId":"f-betavent9mgy9e","leadName":"Beta Ventures","status":"closed","closeDate":"2024-12-20","asOf":"2026-01-04T00:38:52.666Z"},{"id":"r-cclearflwrb7ve","companyId":"c-clearflofn0e0v","stage":"Seed","amt":5520323,"leadId":"f-patelthor252c6","leadName":"Patel & Thompson Fund","status":"closed","closeDate":"2025-03-20","asOf":"2026-01-15T00:38:52.666Z"},{"id":"r-cpulseio2cm9rl","companyId":"c-pulseiof589f4","stage":"Seed","amt":7059024,"leadId":"f-mooretho7y9aeg","leadName":"Moore & Thomas Ventures","status":"closed","closeDate":"2024-06-13","asOf":"2026-01-21T00:38:52.666Z"},{"id":"r-cpulseio4c5i0y","companyId":"c-pulseiof589f4","stage":"Seed","amt":8714214,"leadId":"f-linkventvt3q08","leadName":"Link Ventures","status":"closed","closeDate":"2024-05-09","asOf":"2026-01-28T00:38:52.666Z"},{"id":"r-cpulseiotpwhwo","companyId":"c-pulseiof589f4","stage":"Seed","amt":5490750,"leadId":"f-thompsonzgdo1z","leadName":"Thompson Fund","status":"active","closeDate":"2024-07-07","asOf":"2026-01-08T00:38:52.666Z"},{"id":"r-csafeappvd14ir","companyId":"c-safeappj8a9pf","stage":"Series C","amt":87477221,"leadId":"f-kingfundzfjnk0","leadName":"King Fund","status":"closed","closeDate":"2024-12-30","asOf":"2026-01-09T00:38:52.666Z"},{"id":"r-csafeapp3wu2k6","companyId":"c-safeappj8a9pf","stage":"Series C","amt":98641045,"leadId":"f-nextpart0t887j","leadName":"Next Partners","status":"closed","closeDate":"2025-05-26","asOf":"2026-01-28T00:38:52.666Z"},{"id":"r-catlasop6pvvud","companyId":"c-atlasops9g5u4q","stage":"Series B","amt":18893518,"leadId":"f-cipherin7dqn5z","leadName":"Cipher Investments","status":"closed","closeDate":"2025-03-02","asOf":"2026-01-20T00:38:52.666Z"},{"id":"r-catlasopdae61d","companyId":"c-atlasops9g5u4q","stage":"Series B","amt":37353640,"leadId":"f-orbitinv893k7m","leadName":"Orbit Investments","status":"closed","closeDate":"2024-12-28","asOf":"2026-01-21T00:38:52.666Z"},{"id":"r-cpurepla4y2j5e","companyId":"c-pureplat1gd5ql","stage":"Seed","amt":6496762,"leadId":"f-walkeralgt714k","leadName":"Walker & Allen Fund","status":"closed","closeDate":"2024-02-24","asOf":"2026-01-05T00:38:52.666Z"},{"id":"r-cpureplaw8b1sp","companyId":"c-pureplat1gd5ql","stage":"Seed","amt":4386110,"leadId":"f-firstvczp5hrm","leadName":"First VC","status":"active","closeDate":"2025-02-02","asOf":"2026-01-31T00:38:52.666Z"},{"id":"r-cprismflkc9vi4","companyId":"c-prismflo228sus","stage":"Series C","amt":121419045,"leadId":"f-syncvcd9kzro","leadName":"Sync VC","status":"closed","closeDate":"2024-10-11","asOf":"2026-01-31T00:38:52.666Z"},{"id":"r-cprismflha5btm","companyId":"c-prismflo228sus","stage":"Series C","amt":142068106,"leadId":"f-linkventvt3q08","leadName":"Link Ventures","status":"closed","closeDate":"2025-05-12","asOf":"2026-01-24T00:38:52.666Z"},{"id":"r-csparkpltbrqng","companyId":"c-sparkpla157xm6","stage":"Series A","amt":6652030,"leadId":"f-blueinveyqimzh","leadName":"Blue Investments","status":"closed","closeDate":"2025-04-22","asOf":"2026-01-16T00:38:52.666Z"},{"id":"r-csparkplo1i2i2","companyId":"c-sparkpla157xm6","stage":"Series A","amt":18738080,"leadId":"f-mooreven01pjxz","leadName":"Moore Ventures","status":"closed","closeDate":"2025-10-14","asOf":"2026-01-26T00:38:52.666Z"},{"id":"r-csparkpln2h64f","companyId":"c-sparkpla157xm6","stage":"Series A","amt":5903307,"leadId":"f-datacapircad8h","leadName":"Data Capital","status":"active","closeDate":"2025-12-31","asOf":"2026-01-11T00:38:52.666Z"},{"id":"r-cblueteceqs77w","companyId":"c-bluetechpi1tdf","stage":"Seed","amt":6403589,"leadId":"f-betainveqn8dpy","leadName":"Beta Investments","status":"closed","closeDate":"2025-04-28","asOf":"2026-01-07T00:38:52.666Z"},{"id":"r-cbluetecs9wsog","companyId":"c-bluetechpi1tdf","stage":"Seed","amt":2486569,"leadId":"f-harriscavssyp4","leadName":"Harris Capital","status":"closed","closeDate":"2025-10-02","asOf":"2026-01-11T00:38:52.666Z"},{"id":"r-cblueteczisgd6","companyId":"c-bluetechpi1tdf","stage":"Seed","amt":8312249,"leadId":"f-pulsevcm6vaop","leadName":"Pulse VC","status":"closed","closeDate":"2025-10-23","asOf":"2026-01-26T00:38:52.666Z"},{"id":"r-cquantumevl6ws","companyId":"c-quantumsa6k2u6","stage":"Seed","amt":8230231,"leadId":"f-primeparwnm9hu","leadName":"Prime Partners","status":"active","closeDate":"2025-10-21","asOf":"2026-01-07T00:38:52.666Z"},{"id":"r-cquantumdprjrv","companyId":"c-quantumsa6k2u6","stage":"Seed","amt":4231325,"leadId":"f-firstcapgbkvny","leadName":"First Capital","status":"active","closeDate":"2024-05-21","asOf":"2026-01-21T00:38:52.666Z"},{"id":"r-cquantum7fa72r","companyId":"c-quantumsa6k2u6","stage":"Seed","amt":2321459,"leadId":"f-cloudinvq7zift","leadName":"Cloud Investments","status":"closed","closeDate":"2024-08-21","asOf":"2026-01-08T00:38:52.666Z"},{"id":"r-chelixbaoc1zqr","companyId":"c-helixbasqpxuzq","stage":"Seed","amt":2075507,"leadId":"f-betavent9mgy9e","leadName":"Beta Ventures","status":"closed","closeDate":"2025-06-02","asOf":"2026-01-18T00:38:52.666Z"},{"id":"r-catlasdatqmna0","companyId":"c-atlasdatj8z6f6","stage":"Seed","amt":2736252,"leadId":"f-nextinve9p5e3b","leadName":"Next Investments","status":"closed","closeDate":"2025-09-28","asOf":"2026-01-15T00:38:52.666Z"},{"id":"r-catlasday0jmc1","companyId":"c-atlasdatj8z6f6","stage":"Seed","amt":6908773,"leadId":"f-taylorha6oqlm4","leadName":"Taylor & Hall VC","status":"closed","closeDate":"2025-03-20","asOf":"2026-01-18T00:38:52.666Z"},{"id":"r-catlasdaahyc6n","companyId":"c-atlasdatj8z6f6","stage":"Seed","amt":2667910,"leadId":"f-lewiswilppm9nd","leadName":"Lewis & Williams Ventures","status":"active","closeDate":"2024-03-05","asOf":"2026-01-06T00:38:52.666Z"},{"id":"r-cfasthubg8xync","companyId":"c-fasthubjhou7p","stage":"Seed","amt":9947290,"leadId":"f-williamsxijrmx","leadName":"Williams VC","status":"active","closeDate":"2025-09-23","asOf":"2026-01-23T00:38:52.666Z"},{"id":"r-cfasthubph86tf","companyId":"c-fasthubjhou7p","stage":"Seed","amt":8992245,"leadId":"f-taylorhau7d30q","leadName":"Taylor & Hall Partners","status":"closed","closeDate":"2025-11-27","asOf":"2026-01-31T00:38:52.666Z"},{"id":"r-cflowai2otc04i","companyId":"c-flowai242s6f","stage":"Series C","amt":90978442,"leadId":"f-williamsxijrmx","leadName":"Williams VC","status":"closed","closeDate":"2025-03-12","asOf":"2026-01-13T00:38:52.667Z"},{"id":"r-cflowai2h7quv5","companyId":"c-flowai242s6f","stage":"Series C","amt":147680559,"leadId":"f-bakervc9gt6px","leadName":"Baker VC","status":"active","closeDate":"2024-02-24","asOf":"2026-01-29T00:38:52.667Z"},{"id":"r-copenteccz56om","companyId":"c-opentechgxw83t","stage":"Series A","amt":20296232,"leadId":"f-thompsonwcogpu","leadName":"Thompson & Martin Investments","status":"closed","closeDate":"2024-12-09","asOf":"2026-01-31T00:38:52.667Z"},{"id":"r-clinkclo9pbni6","companyId":"c-linkclouyck9ot","stage":"Seed","amt":9856176,"leadId":"f-corefundivmjcf","leadName":"Core Fund","status":"closed","closeDate":"2025-11-30","asOf":"2026-01-27T00:38:52.667Z"},{"id":"r-cvertexaokljxz","companyId":"c-vertexai6hehya","stage":"Seed","amt":7837723,"leadId":"f-flowcapismmbcg","leadName":"Flow Capital","status":"active","closeDate":"2024-12-21","asOf":"2026-01-20T00:38:52.667Z"},{"id":"r-cvertexaciltzi","companyId":"c-vertexai6hehya","stage":"Seed","amt":4577919,"leadId":"f-newfundmgflhu","leadName":"New Fund","status":"closed","closeDate":"2024-06-03","asOf":"2026-01-31T00:38:52.667Z"},{"id":"r-cvertexardi515","companyId":"c-vertexai6hehya","stage":"Seed","amt":7046889,"leadId":"f-bakerlee1k7az7","leadName":"Baker & Lee Partners","status":"closed","closeDate":"2025-05-03","asOf":"2026-01-08T00:38:52.667Z"},{"id":"r-ccloudlynrkc4v","companyId":"c-cloudlywt58t5","stage":"Series A","amt":14167379,"leadId":"f-primevcfufwr3","leadName":"Prime VC","status":"closed","closeDate":"2025-09-22","asOf":"2026-01-22T00:38:52.667Z"},{"id":"r-ccloudlywe949t","companyId":"c-cloudlywt58t5","stage":"Series A","amt":21033091,"leadId":"f-firstpar0zy7q5","leadName":"First Partners","status":"closed","closeDate":"2025-09-02","asOf":"2026-01-23T00:38:52.667Z"},{"id":"r-ccloudlyyakr6w","companyId":"c-cloudlywt58t5","stage":"Series A","amt":23049324,"leadId":"f-firstven5jttd6","leadName":"First Ventures","status":"active","closeDate":"2024-08-24","asOf":"2026-01-19T00:38:52.667Z"},{"id":"r-cedgeiom0fnj53","companyId":"c-edgeiomxh1yz","stage":"Seed","amt":9835494,"leadId":"f-patelven9qxod1","leadName":"Patel Ventures","status":"closed","closeDate":"2024-03-20","asOf":"2026-01-27T00:38:52.667Z"},{"id":"r-csafeupilda219","companyId":"c-safeupigdp2v","stage":"Seed","amt":4153445,"leadId":"f-kingpartlrayhk","leadName":"King Partners","status":"closed","closeDate":"2025-02-10","asOf":"2026-01-27T00:38:52.667Z"},{"id":"r-csafeupicz71gx","companyId":"c-safeupigdp2v","stage":"Seed","amt":7165352,"leadId":"f-stackinvvn4nfb","leadName":"Stack Investments","status":"closed","closeDate":"2025-11-02","asOf":"2026-01-31T00:38:52.667Z"},{"id":"r-csafeupie2za2m","companyId":"c-safeupigdp2v","stage":"Seed","amt":8768385,"leadId":"f-taylorta3ei5gj","leadName":"Taylor & Taylor Capital","status":"closed","closeDate":"2024-10-27","asOf":"2026-01-04T00:38:52.667Z"},{"id":"r-cstackgobk2fai","companyId":"c-stackgomv326c","stage":"Seed","amt":5676995,"leadId":"f-smithleeiwr723","leadName":"Smith & Lee Ventures","status":"closed","closeDate":"2024-08-02","asOf":"2026-01-18T00:38:52.667Z"},{"id":"r-cstackgo82wtda","companyId":"c-stackgomv326c","stage":"Seed","amt":8352599,"leadId":"f-newcapitbbknru","leadName":"New Capital","status":"closed","closeDate":"2024-12-22","asOf":"2026-01-14T00:38:52.667Z"},{"id":"r-cstackgot7ywm0","companyId":"c-stackgomv326c","stage":"Seed","amt":4076453,"leadId":"f-fastvch7tqxe","leadName":"Fast VC","status":"closed","closeDate":"2025-07-10","asOf":"2026-01-04T00:38:52.667Z"},{"id":"r-corbitlod501ao","companyId":"c-orbitlogyy82g0","stage":"Series A","amt":20420845,"leadId":"f-nextinveowy9nh","leadName":"Next Investments","status":"closed","closeDate":"2024-11-26","asOf":"2026-01-04T00:38:52.667Z"},{"id":"r-cfastanavgtil9","companyId":"c-fastanallgz7aa","stage":"Series A","amt":14400415,"leadId":"f-kiminves0is94n","leadName":"Kim Investments","status":"active","closeDate":"2024-04-17","asOf":"2026-01-16T00:38:52.667Z"},{"id":"r-cfastanahdaoxa","companyId":"c-fastanallgz7aa","stage":"Series A","amt":21250325,"leadId":"f-datafundqq3j3m","leadName":"Data Fund","status":"closed","closeDate":"2024-09-27","asOf":"2026-01-09T00:38:52.667Z"},{"id":"r-cfastanatl0bjc","companyId":"c-fastanallgz7aa","stage":"Series A","amt":14139131,"leadId":"f-newcapit7hbjgp","leadName":"New Capital","status":"closed","closeDate":"2024-03-16","asOf":"2026-01-26T00:38:52.667Z"},{"id":"r-ccloudla47jqei","companyId":"c-cloudlabyi7vj9","stage":"Seed","amt":5006462,"leadId":"f-firstven5jttd6","leadName":"First Ventures","status":"closed","closeDate":"2024-06-18","asOf":"2026-01-05T00:38:52.667Z"},{"id":"r-ccloudla49g34w","companyId":"c-cloudlabyi7vj9","stage":"Seed","amt":7450556,"leadId":"f-nextfundcyu070","leadName":"Next Fund","status":"closed","closeDate":"2024-03-16","asOf":"2026-01-28T00:38:52.667Z"},{"id":"r-cpurehq7w8fsg6","companyId":"c-purehq73kegs","stage":"Series A","amt":24424462,"leadId":"f-betavent6e47az","leadName":"Beta Ventures","status":"closed","closeDate":"2025-05-07","asOf":"2026-01-11T00:38:52.667Z"},{"id":"r-cstackaicds3b7","companyId":"c-stackaic8mhsu","stage":"Seed","amt":8690493,"leadId":"f-firstparmm3kse","leadName":"First Partners","status":"active","closeDate":"2024-06-29","asOf":"2026-01-16T00:38:52.667Z"},{"id":"r-csyncgovjbd47g","companyId":"c-syncgov6v5zj","stage":"Seed","amt":3691364,"leadId":"f-mooreinvepmvtz","leadName":"Moore Investments","status":"active","closeDate":"2025-11-03","asOf":"2026-01-31T00:38:52.667Z"},{"id":"r-csyncgoviypdqu","companyId":"c-syncgov6v5zj","stage":"Seed","amt":5414384,"leadId":"f-linkventvt3q08","leadName":"Link Ventures","status":"active","closeDate":"2024-09-13","asOf":"2026-01-17T00:38:52.667Z"},{"id":"r-csyncgov5cqqa5","companyId":"c-syncgov6v5zj","stage":"Seed","amt":3076173,"leadId":"f-openinvechfvgt","leadName":"Open Investments","status":"closed","closeDate":"2024-02-24","asOf":"2026-01-30T00:38:52.667Z"},{"id":"r-cfastclorn9rrt","companyId":"c-fastclou3xfsdh","stage":"Seed","amt":8865046,"leadId":"f-youngthocip3xy","leadName":"Young & Thomas Ventures","status":"active","closeDate":"2025-03-19","asOf":"2026-01-07T00:38:52.667Z"},{"id":"r-cfastclos4crym","companyId":"c-fastclou3xfsdh","stage":"Seed","amt":8072600,"leadId":"f-newfund4tvrey","leadName":"New Fund","status":"closed","closeDate":"2024-02-26","asOf":"2026-01-18T00:38:52.667Z"},{"id":"r-cdataairpiaj7e","companyId":"c-dataairbqhw3","stage":"Series A","amt":14911644,"leadId":"f-newcapitevwfxj","leadName":"New Capital","status":"active","closeDate":"2025-12-17","asOf":"2026-01-15T00:38:52.667Z"},{"id":"r-cclearlaojndl5","companyId":"c-clearlaby1epaj","stage":"Series A","amt":10516925,"leadId":"f-harrisal2wv103","leadName":"Harris & Allen Ventures","status":"closed","closeDate":"2024-08-12","asOf":"2026-01-13T00:38:52.667Z"},{"id":"r-cclearlawuplvt","companyId":"c-clearlaby1epaj","stage":"Series A","amt":5142934,"leadId":"f-chenwhitzy5pmd","leadName":"Chen & White Ventures","status":"active","closeDate":"2024-10-11","asOf":"2026-01-27T00:38:52.667Z"},{"id":"r-cclearlal59vrv","companyId":"c-clearlaby1epaj","stage":"Series A","amt":20125029,"leadId":"f-prismcappr4hwi","leadName":"Prism Capital","status":"closed","closeDate":"2025-06-21","asOf":"2026-01-29T00:38:52.667Z"},{"id":"r-cvertexs3j4ra2","companyId":"c-vertexsolbrkev","stage":"Seed","amt":7602634,"leadId":"f-atlaspari6kwyv","leadName":"Atlas Partners","status":"closed","closeDate":"2025-02-03","asOf":"2026-01-03T00:38:52.667Z"},{"id":"r-cvertexs1daonw","companyId":"c-vertexsolbrkev","stage":"Seed","amt":6622697,"leadId":"f-kiminvesxu67oc","leadName":"Kim Investments","status":"closed","closeDate":"2025-01-23","asOf":"2026-01-03T00:38:52.667Z"},{"id":"r-cvertexs44wqar","companyId":"c-vertexsolbrkev","stage":"Seed","amt":9304424,"leadId":"f-flowparti8k1dw","leadName":"Flow Partners","status":"active","closeDate":"2024-12-02","asOf":"2026-01-15T00:38:52.667Z"},{"id":"r-cvectorxnfhe1u","companyId":"c-vectorx5bjyx3","stage":"Seed","amt":5111853,"leadId":"f-firstvczp5hrm","leadName":"First VC","status":"closed","closeDate":"2025-11-28","asOf":"2026-01-15T00:38:52.667Z"},{"id":"r-cvectorx83xf3v","companyId":"c-vectorx5bjyx3","stage":"Seed","amt":5631907,"leadId":"f-taylorch3s2lrh","leadName":"Taylor & Chen Partners","status":"closed","closeDate":"2024-03-03","asOf":"2026-01-21T00:38:52.667Z"},{"id":"r-cpulseuppll7qg","companyId":"c-pulseuph5l3qv","stage":"Series B","amt":27923706,"leadId":"f-newfunddc5bdy","leadName":"New Fund","status":"closed","closeDate":"2025-06-29","asOf":"2026-01-03T00:38:52.667Z"},{"id":"r-cprismif978utu","companyId":"c-prismifyik2unn","stage":"Seed","amt":4024330,"leadId":"f-vertexpab25xd9","leadName":"Vertex Partners","status":"active","closeDate":"2024-11-27","asOf":"2026-01-25T00:38:52.667Z"},{"id":"r-cprismif4oqkyg","companyId":"c-prismifyik2unn","stage":"Seed","amt":9481450,"leadId":"f-prisminvxhfph8","leadName":"Prism Investments","status":"closed","closeDate":"2025-02-23","asOf":"2026-01-17T00:38:52.667Z"},{"id":"r-csynciot5779x3","companyId":"c-synciot3g68h","stage":"Seed","amt":5127778,"leadId":"f-scottgreo93jdv","leadName":"Scott & Green Capital","status":"closed","closeDate":"2024-07-07","asOf":"2026-01-08T00:38:52.667Z"},{"id":"r-capextecj0zuvs","companyId":"c-apextechl9x1xm","stage":"Series A","amt":6087887,"leadId":"f-newcapit7hbjgp","leadName":"New Capital","status":"active","closeDate":"2025-06-16","asOf":"2026-02-01T00:38:52.667Z"},{"id":"r-capextecei6mju","companyId":"c-apextechl9x1xm","stage":"Series A","amt":20106287,"leadId":"f-primeparwnm9hu","leadName":"Prime Partners","status":"closed","closeDate":"2025-02-10","asOf":"2026-01-11T00:38:52.667Z"},{"id":"r-capextec1ohpbi","companyId":"c-apextechl9x1xm","stage":"Series A","amt":15517302,"leadId":"f-martinwahdyqmp","leadName":"Martin & Walker Fund","status":"closed","closeDate":"2025-10-15","asOf":"2026-01-10T00:38:52.667Z"},{"id":"r-cnetsolu3nr5ji","companyId":"c-netsolutoxcauk","stage":"Seed","amt":4959422,"leadId":"f-bakerveniqyhk1","leadName":"Baker Ventures","status":"closed","closeDate":"2025-02-16","asOf":"2026-01-03T00:38:52.667Z"},{"id":"r-cnetsoluojbdxa","companyId":"c-netsolutoxcauk","stage":"Seed","amt":2809091,"leadId":"f-betapartpf9knz","leadName":"Beta Partners","status":"active","closeDate":"2025-09-26","asOf":"2026-01-03T00:38:52.667Z"},{"id":"r-cnetsoluaendzo","companyId":"c-netsolutoxcauk","stage":"Seed","amt":3727788,"leadId":"f-wrightwhwhznad","leadName":"Wright & White Fund","status":"closed","closeDate":"2025-03-06","asOf":"2026-01-27T00:38:52.667Z"},{"id":"r-cvertexpj9yhq3","companyId":"c-vertexpld9kq9v","stage":"Series A","amt":11567398,"leadId":"f-adamscapre19fr","leadName":"Adams Capital","status":"closed","closeDate":"2024-10-04","asOf":"2026-01-14T00:38:52.667Z"},{"id":"r-csafelyvkq7hk9","companyId":"c-safelyv1l9kj","stage":"Series A","amt":22489999,"leadId":"f-patelinv9ba8iv","leadName":"Patel Investments","status":"closed","closeDate":"2024-12-24","asOf":"2026-01-18T00:38:52.667Z"},{"id":"r-csafelyvgudubq","companyId":"c-safelyv1l9kj","stage":"Series A","amt":12909909,"leadId":"f-bridgepad8nnnu","leadName":"Bridge Partners","status":"closed","closeDate":"2024-10-21","asOf":"2026-01-11T00:38:52.667Z"},{"id":"r-csafelyvszcflt","companyId":"c-safelyv1l9kj","stage":"Series A","amt":7657153,"leadId":"f-lopezvenj5pqlt","leadName":"Lopez Ventures","status":"closed","closeDate":"2025-09-10","asOf":"2026-01-09T00:38:52.667Z"},{"id":"r-cnovaopseq27aa","companyId":"c-novaopsk17m95","stage":"Series A","amt":10604915,"leadId":"f-primeinvglrnvt","leadName":"Prime Investments","status":"active","closeDate":"2025-10-03","asOf":"2026-01-11T00:38:52.667Z"},{"id":"r-cnovaopsvkiac4","companyId":"c-novaopsk17m95","stage":"Series A","amt":19031498,"leadId":"f-firstvcmg9x9j","leadName":"First VC","status":"closed","closeDate":"2025-02-11","asOf":"2026-01-26T00:38:52.667Z"},{"id":"r-cvertexuwbjpne","companyId":"c-vertexupv41989","stage":"Series A","amt":8105662,"leadId":"f-betacapip9kkfi","leadName":"Beta Capital","status":"closed","closeDate":"2024-08-22","asOf":"2026-01-17T00:38:52.667Z"},{"id":"r-cpulseopyuxbqf","companyId":"c-pulseopsjex165","stage":"Seed","amt":7105736,"leadId":"f-betafundq0abph","leadName":"Beta Fund","status":"closed","closeDate":"2024-10-04","asOf":"2026-01-20T00:38:52.667Z"},{"id":"r-cbridgepvbsqxz","companyId":"c-bridgepl7hc4di","stage":"Seed","amt":5807391,"leadId":"f-vertexcafxueg1","leadName":"Vertex Capital","status":"closed","closeDate":"2025-06-07","asOf":"2026-01-16T00:38:52.667Z"},{"id":"r-cbridgepozhysx","companyId":"c-bridgepl7hc4di","stage":"Seed","amt":2677978,"leadId":"f-kimanderw3xfiz","leadName":"Kim & Anderson Fund","status":"closed","closeDate":"2024-08-23","asOf":"2026-01-17T00:38:52.667Z"},{"id":"r-chelixpl9vb6kt","companyId":"c-helixplagi1bcp","stage":"Seed","amt":6431786,"leadId":"f-kiminvesxu67oc","leadName":"Kim Investments","status":"closed","closeDate":"2024-07-23","asOf":"2026-01-06T00:38:52.667Z"},{"id":"r-chelixplt2w0ri","companyId":"c-helixplagi1bcp","stage":"Seed","amt":8978360,"leadId":"f-prismvc8oog2v","leadName":"Prism VC","status":"active","closeDate":"2025-01-05","asOf":"2026-01-06T00:38:52.667Z"},{"id":"r-cdatalab85gmgu","companyId":"c-datalabskt99mu","stage":"Series A","amt":17102242,"leadId":"f-harrisal2wv103","leadName":"Harris & Allen Ventures","status":"active","closeDate":"2025-12-03","asOf":"2026-01-20T00:38:52.667Z"},{"id":"r-catlasflewoq47","companyId":"c-atlasflolhr753","stage":"Seed","amt":5038067,"leadId":"f-betainve2vorik","leadName":"Beta Investments","status":"closed","closeDate":"2024-11-01","asOf":"2026-01-31T00:38:52.667Z"},{"id":"r-cquantumrkue5r","companyId":"c-quantuma01fwrf","stage":"Seed","amt":6617039,"leadId":"f-lopezvcu8gs8q","leadName":"Lopez VC","status":"closed","closeDate":"2025-07-04","asOf":"2026-01-24T00:38:52.667Z"},{"id":"r-cquantums8ohld","companyId":"c-quantuma01fwrf","stage":"Seed","amt":5521613,"leadId":"f-quantumir1ucnh","leadName":"Quantum Investments","status":"active","closeDate":"2024-04-24","asOf":"2026-01-07T00:38:52.667Z"},{"id":"r-cquantumgsco8s","companyId":"c-quantuma01fwrf","stage":"Seed","amt":5292597,"leadId":"f-truevcbe95e5","leadName":"True VC","status":"closed","closeDate":"2025-03-11","asOf":"2026-01-17T00:38:52.667Z"},{"id":"r-csafeappe2xwmb","companyId":"c-safeapplbpmlj","stage":"Series C","amt":138045739,"leadId":"f-newventuo2a6ix","leadName":"New Ventures","status":"closed","closeDate":"2025-09-21","asOf":"2026-01-31T00:38:52.667Z"},{"id":"r-csafeappi8aqc5","companyId":"c-safeapplbpmlj","stage":"Series C","amt":130896493,"leadId":"f-betainveqn8dpy","leadName":"Beta Investments","status":"active","closeDate":"2025-02-21","asOf":"2026-01-18T00:38:52.667Z"},{"id":"r-cnexusaipe0f71","companyId":"c-nexusaijpjo8j","stage":"Series A","amt":13943225,"leadId":"f-kingalleds5h4u","leadName":"King & Allen Capital","status":"closed","closeDate":"2024-12-28","asOf":"2026-01-18T00:38:52.667Z"},{"id":"r-cnexusaiajnhtm","companyId":"c-nexusaijpjo8j","stage":"Series A","amt":5737049,"leadId":"f-adamscapvjvjky","leadName":"Adams Capital","status":"closed","closeDate":"2025-05-30","asOf":"2026-01-25T00:38:52.667Z"},{"id":"r-csmartup5slscs","companyId":"c-smartupi37qq9","stage":"Series B","amt":44154642,"leadId":"f-wrightbaa8wn82","leadName":"Wright & Baker VC","status":"closed","closeDate":"2024-03-07","asOf":"2026-01-10T00:38:52.667Z"},{"id":"r-cfluxgowbcbio6","companyId":"c-fluxgowb62xo","stage":"Seed","amt":9224576,"leadId":"f-thomascahf8600","leadName":"Thomas Capital","status":"closed","closeDate":"2024-11-09","asOf":"2026-01-14T00:38:52.667Z"},{"id":"r-cfluxgowsw1990","companyId":"c-fluxgowb62xo","stage":"Seed","amt":3874139,"leadId":"f-thomascahf8600","leadName":"Thomas Capital","status":"active","closeDate":"2025-10-18","asOf":"2026-01-09T00:38:52.667Z"},{"id":"r-cfluxgow74bd0t","companyId":"c-fluxgowb62xo","stage":"Seed","amt":4931169,"leadId":"f-truevcnx3l4c","leadName":"True VC","status":"closed","closeDate":"2025-12-20","asOf":"2026-01-20T00:38:52.667Z"},{"id":"r-cpulsehuxg0hrs","companyId":"c-pulsehubot1sbi","stage":"Series B","amt":24292803,"leadId":"f-newpartncguwx6","leadName":"New Partners","status":"closed","closeDate":"2024-09-03","asOf":"2026-01-25T00:38:52.667Z"},{"id":"r-cflowlogtyv4xu","companyId":"c-flowlogi97wiqp","stage":"Series A","amt":10696366,"leadId":"f-alphavci3fkon","leadName":"Alpha VC","status":"closed","closeDate":"2025-07-29","asOf":"2026-01-29T00:38:52.667Z"},{"id":"r-clinkclonvxnyv","companyId":"c-linkclouf6whdt","stage":"Series B","amt":22475050,"leadId":"f-trueventumohw4","leadName":"True Ventures","status":"active","closeDate":"2024-06-30","asOf":"2026-01-19T00:38:52.667Z"},{"id":"r-cquantumzvse5h","companyId":"c-quantumtjd0kg2","stage":"Series A","amt":6555870,"leadId":"f-clarkven4y5622","leadName":"Clark Ventures","status":"closed","closeDate":"2024-09-15","asOf":"2026-01-24T00:38:52.667Z"},{"id":"r-cpureaix55bu03","companyId":"c-pureaixdhcze","stage":"Series A","amt":11612963,"leadId":"f-pulsevcm6vaop","leadName":"Pulse VC","status":"active","closeDate":"2024-05-19","asOf":"2026-01-14T00:38:52.667Z"},{"id":"r-clinkopst1uara","companyId":"c-linkops162snc","stage":"Series A","amt":23205836,"leadId":"f-hallwillm3h6fn","leadName":"Hall & Williams Investments","status":"closed","closeDate":"2025-09-28","asOf":"2026-01-19T00:38:52.667Z"},{"id":"r-clinktecm607lk","companyId":"c-linktechdsnelk","stage":"Seed","amt":2301725,"leadId":"f-cloudvc9my07z","leadName":"Cloud VC","status":"closed","closeDate":"2024-05-10","asOf":"2026-01-04T00:38:52.667Z"},{"id":"r-copenwor0iefbj","companyId":"c-openworkxtii7h","stage":"Series A","amt":24800428,"leadId":"f-taylorinem73f2","leadName":"Taylor Investments","status":"active","closeDate":"2024-11-17","asOf":"2026-02-01T00:38:52.667Z"},{"id":"r-copenworjd6kve","companyId":"c-openworkxtii7h","stage":"Series A","amt":21717584,"leadId":"f-martinezjemn2c","leadName":"Martinez & King Fund","status":"closed","closeDate":"2024-09-14","asOf":"2026-01-05T00:38:52.667Z"},{"id":"r-copenworalzw8p","companyId":"c-openworkxtii7h","stage":"Series A","amt":10614423,"leadId":"f-patelvcc6nfay","leadName":"Patel VC","status":"active","closeDate":"2024-04-10","asOf":"2026-01-29T00:38:52.667Z"},{"id":"r-cdataifyl7idwv","companyId":"c-dataify06dge5","stage":"Seed","amt":9002328,"leadId":"f-johnsoncg81vsx","leadName":"Johnson Capital","status":"closed","closeDate":"2024-07-01","asOf":"2026-01-15T00:38:52.667Z"},{"id":"r-ccoresofqnx9uh","companyId":"c-coresoft46whfe","stage":"Series A","amt":9774048,"leadId":"f-flowparti8k1dw","leadName":"Flow Partners","status":"closed","closeDate":"2025-04-01","asOf":"2026-01-17T00:38:52.667Z"},{"id":"r-cblueaiwrhtsyz","companyId":"c-blueaiwuizln","stage":"Seed","amt":5201398,"leadId":"f-quantumit9wzsh","leadName":"Quantum Investments","status":"closed","closeDate":"2025-03-19","asOf":"2026-01-23T00:38:52.667Z"},{"id":"r-csafeaibzh1jk8","companyId":"c-safeaibm36rs","stage":"Series B","amt":35299243,"leadId":"f-bluefund7befo0","leadName":"Blue Fund","status":"closed","closeDate":"2025-05-27","asOf":"2026-01-23T00:38:52.667Z"},{"id":"r-csafeaibou6897","companyId":"c-safeaibm36rs","stage":"Series B","amt":44171235,"leadId":"f-cloudvc9my07z","leadName":"Cloud VC","status":"active","closeDate":"2025-07-14","asOf":"2026-01-17T00:38:52.667Z"},{"id":"r-csafeaibs84oeo","companyId":"c-safeaibm36rs","stage":"Series B","amt":32507864,"leadId":"f-greenfunf8t72l","leadName":"Green Fund","status":"closed","closeDate":"2024-11-18","asOf":"2026-01-21T00:38:52.667Z"},{"id":"r-cbluegon6qnbfp","companyId":"c-bluegoncqr3r","stage":"Seed","amt":9272579,"leadId":"f-mooreinvepmvtz","leadName":"Moore Investments","status":"active","closeDate":"2024-09-24","asOf":"2026-01-06T00:38:52.667Z"},{"id":"r-cbluegon02fq7f","companyId":"c-bluegoncqr3r","stage":"Seed","amt":4210473,"leadId":"f-quantumpeszf1u","leadName":"Quantum Partners","status":"closed","closeDate":"2024-04-08","asOf":"2026-01-11T00:38:52.667Z"},{"id":"r-cbluebaswk6hik","companyId":"c-bluebasevnjusv","stage":"Series A","amt":12226715,"leadId":"f-johnsonptxvf25","leadName":"Johnson Partners","status":"closed","closeDate":"2024-03-01","asOf":"2026-01-15T00:38:52.667Z"},{"id":"r-cbluebaszq1thv","companyId":"c-bluebasevnjusv","stage":"Series A","amt":14643696,"leadId":"f-wrightinhhf1oy","leadName":"Wright Investments","status":"closed","closeDate":"2025-09-01","asOf":"2026-01-28T00:38:52.667Z"},{"id":"r-ccipherw96aa00","companyId":"c-cipherwolr5nnh","stage":"Series B","amt":24932840,"leadId":"f-hallwillm3h6fn","leadName":"Hall & Williams Investments","status":"closed","closeDate":"2024-10-29","asOf":"2026-01-06T00:38:52.667Z"},{"id":"r-ccipherwp96jze","companyId":"c-cipherwolr5nnh","stage":"Series B","amt":31150023,"leadId":"f-edgevcw3ubsi","leadName":"Edge VC","status":"closed","closeDate":"2024-12-09","asOf":"2026-01-10T00:38:52.667Z"},{"id":"r-ccipherw0c3agm","companyId":"c-cipherwolr5nnh","stage":"Series B","amt":31479124,"leadId":"f-thompsonzgdo1z","leadName":"Thompson Fund","status":"closed","closeDate":"2024-04-17","asOf":"2026-01-09T00:38:52.667Z"},{"id":"r-cedgelogt321nj","companyId":"c-edgelogi8mxljx","stage":"Series B","amt":24535549,"leadId":"f-martinan3dbmmp","leadName":"Martin & Anderson Ventures","status":"closed","closeDate":"2024-08-26","asOf":"2026-01-05T00:38:52.667Z"},{"id":"r-cedgelogu3lr1j","companyId":"c-edgelogi8mxljx","stage":"Series B","amt":43384421,"leadId":"f-helixparjbt2gu","leadName":"Helix Partners","status":"closed","closeDate":"2024-07-24","asOf":"2026-01-04T00:38:52.667Z"},{"id":"r-cedgelog9cal71","companyId":"c-edgelogi8mxljx","stage":"Series B","amt":49314529,"leadId":"f-primevcnkm24u","leadName":"Prime VC","status":"closed","closeDate":"2025-12-05","asOf":"2026-01-09T00:38:52.667Z"},{"id":"r-ccleargos27j8t","companyId":"c-cleargo3mtv18","stage":"Seed","amt":9246628,"leadId":"f-datacapircad8h","leadName":"Data Capital","status":"active","closeDate":"2025-01-25","asOf":"2026-01-21T00:38:52.667Z"},{"id":"r-ccleargodiubqj","companyId":"c-cleargo3mtv18","stage":"Seed","amt":6607270,"leadId":"f-syncvcd9kzro","leadName":"Sync VC","status":"closed","closeDate":"2025-06-21","asOf":"2026-01-04T00:38:52.667Z"},{"id":"r-cbridgecsfjc3y","companyId":"c-bridgecltzhyt4","stage":"Seed","amt":4774396,"leadId":"f-vertexpab25xd9","leadName":"Vertex Partners","status":"closed","closeDate":"2024-06-18","asOf":"2026-01-17T00:38:52.667Z"},{"id":"r-cbridgecxu7v1j","companyId":"c-bridgecltzhyt4","stage":"Seed","amt":8211773,"leadId":"f-purepart7hd1jz","leadName":"Pure Partners","status":"closed","closeDate":"2025-07-05","asOf":"2026-01-10T00:38:52.667Z"},{"id":"r-cbridgec4bnlt4","companyId":"c-bridgecltzhyt4","stage":"Seed","amt":7903096,"leadId":"f-rodrigue9ycoue","leadName":"Rodriguez Investments","status":"active","closeDate":"2024-11-10","asOf":"2026-01-19T00:38:52.667Z"},{"id":"r-cfluxsof038y5g","companyId":"c-fluxsoftke7354","stage":"Seed","amt":7424879,"leadId":"f-johnsonv33au3o","leadName":"Johnson Ventures","status":"active","closeDate":"2024-08-24","asOf":"2026-01-15T00:38:52.667Z"},{"id":"r-csyncai9a5xt62","companyId":"c-syncai9849ws","stage":"Seed","amt":7917231,"leadId":"f-flowparti8k1dw","leadName":"Flow Partners","status":"closed","closeDate":"2024-08-04","asOf":"2026-01-19T00:38:52.667Z"},{"id":"r-csyncai98fkc9b","companyId":"c-syncai9849ws","stage":"Seed","amt":3924588,"leadId":"f-martinwi8xondn","leadName":"Martin & Williams Partners","status":"closed","closeDate":"2024-11-19","asOf":"2026-01-09T00:38:52.667Z"},{"id":"r-cbluehqztmpymq","companyId":"c-bluehqz7r0sk","stage":"Seed","amt":2722531,"leadId":"f-chenwhitzy5pmd","leadName":"Chen & White Ventures","status":"closed","closeDate":"2025-09-25","asOf":"2026-01-09T00:38:52.667Z"},{"id":"r-cbluehqzctol0n","companyId":"c-bluehqz7r0sk","stage":"Seed","amt":3833884,"leadId":"f-johnsonv33au3o","leadName":"Johnson Ventures","status":"closed","closeDate":"2025-08-08","asOf":"2026-01-23T00:38:52.667Z"},{"id":"r-cbluehqz4g9wwg","companyId":"c-bluehqz7r0sk","stage":"Seed","amt":5588415,"leadId":"f-newventuo2a6ix","leadName":"New Ventures","status":"active","closeDate":"2025-06-15","asOf":"2026-01-28T00:38:52.667Z"},{"id":"r-csmartla8a8wyg","companyId":"c-smartlabf3hjbo","stage":"Series C","amt":57936122,"leadId":"f-walkerrokz76gw","leadName":"Walker & Rodriguez Ventures","status":"closed","closeDate":"2025-10-13","asOf":"2026-01-17T00:38:52.667Z"},{"id":"r-cgridaimwh4zbv","companyId":"c-gridaimrrufi","stage":"Series A","amt":18962157,"leadId":"f-bakerlee1k7az7","leadName":"Baker & Lee Partners","status":"active","closeDate":"2024-05-13","asOf":"2026-01-14T00:38:52.667Z"},{"id":"r-cblueflo822z6l","companyId":"c-blueflowj007af","stage":"Series A","amt":16917326,"leadId":"f-newfund4tvrey","leadName":"New Fund","status":"active","closeDate":"2025-11-07","asOf":"2026-01-18T00:38:52.667Z"},{"id":"r-cblueflod6n6ya","companyId":"c-blueflowj007af","stage":"Series A","amt":22490118,"leadId":"f-bakerveniqyhk1","leadName":"Baker Ventures","status":"active","closeDate":"2025-08-23","asOf":"2026-01-08T00:38:52.667Z"},{"id":"r-cblueflormnhrg","companyId":"c-blueflowj007af","stage":"Series A","amt":23403217,"leadId":"f-bakervc9gt6px","leadName":"Baker VC","status":"closed","closeDate":"2024-06-04","asOf":"2026-01-26T00:38:52.667Z"},{"id":"r-cfastbasf9vsdw","companyId":"c-fastbasewogldp","stage":"Series A","amt":10157155,"leadId":"f-betavcptp5kz","leadName":"Beta VC","status":"active","closeDate":"2025-06-05","asOf":"2026-01-18T00:38:52.667Z"},{"id":"r-cfastbasv7pokh","companyId":"c-fastbasewogldp","stage":"Series A","amt":16136486,"leadId":"f-thompsonr50h9l","leadName":"Thompson VC","status":"closed","closeDate":"2024-04-26","asOf":"2026-01-26T00:38:52.667Z"},{"id":"r-cfastbas6yhs5h","companyId":"c-fastbasewogldp","stage":"Series A","amt":16458124,"leadId":"f-nextinve49zlgo","leadName":"Next Investments","status":"closed","closeDate":"2025-10-14","asOf":"2026-01-27T00:38:52.667Z"},{"id":"r-cflowlynx1ciif","companyId":"c-flowlynsncfa","stage":"Series A","amt":8722669,"leadId":"f-patelfun3dimi5","leadName":"Patel Fund","status":"closed","closeDate":"2025-06-26","asOf":"2026-01-16T00:38:52.667Z"},{"id":"r-cflowlyn9knfg0","companyId":"c-flowlynsncfa","stage":"Series A","amt":23848416,"leadId":"f-vectorvemy5k5q","leadName":"Vector Ventures","status":"closed","closeDate":"2024-07-26","asOf":"2026-01-24T00:38:52.667Z"},{"id":"r-cbridgeflbmwvp","companyId":"c-bridgefl8vrsbp","stage":"Seed","amt":6651669,"leadId":"f-purepart7hd1jz","leadName":"Pure Partners","status":"closed","closeDate":"2024-12-09","asOf":"2026-01-05T00:38:52.667Z"},{"id":"r-cbridgefv1s4mn","companyId":"c-bridgefl8vrsbp","stage":"Seed","amt":8689885,"leadId":"f-newfund4tvrey","leadName":"New Fund","status":"active","closeDate":"2024-12-08","asOf":"2026-01-26T00:38:52.667Z"},{"id":"r-cfasthubgpgy3y","companyId":"c-fasthubjghqrl","stage":"Series A","amt":8952812,"leadId":"f-lopezwriii19tb","leadName":"Lopez & Wright Partners","status":"active","closeDate":"2025-01-23","asOf":"2026-01-09T00:38:52.667Z"},{"id":"r-cfasthubo4e0uw","companyId":"c-fasthubjghqrl","stage":"Series A","amt":5460858,"leadId":"f-bluecapi8jdmzw","leadName":"Blue Capital","status":"active","closeDate":"2025-06-13","asOf":"2026-01-31T00:38:52.667Z"},{"id":"r-cfastxo2jb289v","companyId":"c-fastxo2kbdb","stage":"Series A","amt":19925352,"leadId":"f-rodrigueuyuuuo","leadName":"Rodriguez & Johnson Fund","status":"closed","closeDate":"2024-04-18","asOf":"2026-01-18T00:38:52.667Z"},{"id":"r-cprismpl0ikbdc","companyId":"c-prismplau9hpqy","stage":"Series A","amt":8139356,"leadId":"f-bakercaphuwwfx","leadName":"Baker Capital","status":"closed","closeDate":"2025-04-03","asOf":"2026-01-05T00:38:52.667Z"},{"id":"r-cprismpltgzjw5","companyId":"c-prismplau9hpqy","stage":"Series A","amt":16201692,"leadId":"f-chenhallqt79cb","leadName":"Chen & Hall Partners","status":"active","closeDate":"2024-05-14","asOf":"2026-01-05T00:38:52.667Z"}]